lca_third_party/__init__.py
lca_third_party/payment_client.py
lca_third_party-0.2.0.dist-info/WHEEL
lca_third_party-0.2.0.dist-info/METADATA
lca_third_party-0.2.0.dist-info/RECORD
