Metadata-Version: 2.1
Name: lca-third-party
Version: 0.2.0
Summary: Exemplary third party library for LCA 2023
Author: Michał Chałupczak
Requires-Python: >=3.7,<4.0
Classifier: Programming Language :: Python :: 3
Classifier: Programming Language :: Python :: 3.7
Classifier: Programming Language :: Python :: 3.8
Classifier: Programming Language :: Python :: 3.9
Classifier: Programming Language :: Python :: 3.10
Classifier: Programming Language :: Python :: 3.11
